reflectapi_runtime/__init__.py
reflectapi_runtime/auth.py
reflectapi_runtime/batch.py
reflectapi_runtime/client.py
reflectapi_runtime/exceptions.py
reflectapi_runtime/hypothesis_strategies.py
reflectapi_runtime/middleware.py
reflectapi_runtime/option.py
reflectapi_runtime/response.py
reflectapi_runtime/streaming.py
reflectapi_runtime/testing.py
reflectapi_runtime/types.py
reflectapi_runtime-0.1.0.dist-info/METADATA
reflectapi_runtime-0.1.0.dist-info/WHEEL
reflectapi_runtime-0.1.0.dist-info/RECORD
